Workbook

Sheet Assumptions
A1: DUM Club Profit Model — Assumptions (blue cells = change me)
A3: FIXED MONTHLY COSTS (platform, regardless of merchants)
A4: Vercel (frontend hosting, Pro) | B4: 20
A5: Railway (backend API + cron services) | B5: 20
A6: Supabase (database, Pro) | B6: 25
A7: Resend (email) | B7: 20
A8: Privy (auth) | B8: 0
A9: Domains (GoDaddy, monthly-ized) | B9: 5
A10: Anthropic API (AI chat features) | B10: 20
A12: VARIABLE COST RATES (verified)
A13: AWS IVS cost per viewer-hour ($) [aws.amazon.com/ivs/pricing, 2026-07] | B13: 0.072
A14: Stripe fee on subscription collections (%) | B14: 0.029
A15: Stripe fixed fee per subscription charge ($) | B15: 0.3
A17: PER-SHOP BEHAVIOR (change for scenarios)
A18: Avg viewer-hours used per shop / month | B18: 100
A19: Avg GMV per shop / month ($) | B19: 2000
A20: Platform sales fee (%) | B20: 0.015
A22: TIER PRICES ($/mo)
A23: Starter | B23: 39
A24: Growth | B24: 99
A25: Pro | B25: 299
A26: Included viewer-hours: Starter | B26: 250
A27: Included viewer-hours: Growth | B27: 700
A28: Included viewer-hours: Pro | B28: 1500
A29: Overage rate: Starter ($/vh) | B29: 0.13
A30: Overage rate: Growth ($/vh) | B30: 0.12
A31: Overage rate: Pro ($/vh) | B31: 0.1

Sheet Per-Shop P&L
A1: Monthly profit per shop, by tier (at the behavior set in Assumptions)
B3: Starter | C3: Growth | D3: Pro
A4: Subscription revenue | B4: =Assumptions!$B$23 -> 39 | C4: =Assumptions!$B$24 -> 99 | D4: =Assumptions!$B$25 -> 299
A5: Sales-fee revenue (GMV × fee) | B5: =Assumptions!$B$19*Assumptions!$B$20 -> 30 | C5: =Assumptions!$B$19*Assumptions!$B$20 -> 30 | D5: =Assumptions!$B$19*Assumptions!$B$20 -> 30
A6: Overage billed (after no-double-bill waiver) | B6: =MAX(0,MAX(0,Assumptions!$B$18-Assumptions!$B$26)*Assumptions!$B$29-Assumptions!$B$19*Assumptions!$B$20) -> 0 | C6: =MAX(0,MAX(0,Assumptions!$B$18-Assumptions!$B$27)*Assumptions!$B$30-Assumptions!$B$19*Assumptions!$B$20) -> 0 | D6: =MAX(0,MAX(0,Assumptions!$B$18-Assumptions!$B$28)*Assumptions!$B$31-Assumptions!$B$19*Assumptions!$B$20) -> 0
A7: Total revenue | B7: =B4+B5+B6 -> 69 | C7: =C4+C5+C6 -> 129 | D7: =D4+D5+D6 -> 329
A8: AWS streaming cost (vh × IVS rate) | B8: =-Assumptions!$B$18*Assumptions!$B$13 -> -7.2 | C8: =-Assumptions!$B$18*Assumptions!$B$13 -> -7.2 | D8: =-Assumptions!$B$18*Assumptions!$B$13 -> -7.2
A9: Stripe fee on subscription | B9: =-(Assumptions!$B$23*Assumptions!$B$14+Assumptions!$B$15) -> -1.431 | C9: =-(Assumptions!$B$24*Assumptions!$B$14+Assumptions!$B$15) -> -3.171 | D9: =-(Assumptions!$B$25*Assumptions!$B$14+Assumptions!$B$15) -> -8.971
A10: Profit per shop / month | B10: =B7+B8+B9 -> 60.369 | C10: =C7+C8+C9 -> 118.629 | D10: =D7+D8+D9 -> 312.829
A11: Margin | B11: =IF(B7=0,0,B10/B7) -> 0.87491304 | C11: =IF(C7=0,0,C10/C7) -> 0.91960465 | D11: =IF(D7=0,0,D10/D7) -> 0.95084802

Sheet Platform P&L
A1: Platform monthly profit at N shops (all Starter, behavior per Assumptions)
A3: Shops | B3: Revenue | C3: Variable costs | D3: Fixed costs | E3: Profit / month | F3: Profit / year
A4: 0 | B4: =A4*('Per-Shop P&L'!B7) -> 0 | C4: =A4*('Per-Shop P&L'!B8+'Per-Shop P&L'!B9) -> 0 | D4: =-(Assumptions!$B$4+Assumptions!$B$5+Assumptions!$B$6+Assumptions!$B$7+Assumptions!$B$8+Assumptions!$B$9+Assumptions!$B$10) -> -110 | E4: =B4+C4+D4 -> -110 | F4: =E4*12 -> -1320
A5: 1 | B5: =A5*('Per-Shop P&L'!B7) -> 69 | C5: =A5*('Per-Shop P&L'!B8+'Per-Shop P&L'!B9) -> -8.631 | D5: =-(Assumptions!$B$4+Assumptions!$B$5+Assumptions!$B$6+Assumptions!$B$7+Assumptions!$B$8+Assumptions!$B$9+Assumptions!$B$10) -> -110 | E5: =B5+C5+D5 -> -49.631 | F5: =E5*12 -> -595.572
A6: 3 | B6: =A6*('Per-Shop P&L'!B7) -> 207 | C6: =A6*('Per-Shop P&L'!B8+'Per-Shop P&L'!B9) -> -25.893 | D6: =-(Assumptions!$B$4+Assumptions!$B$5+Assumptions!$B$6+Assumptions!$B$7+Assumptions!$B$8+Assumptions!$B$9+Assumptions!$B$10) -> -110 | E6: =B6+C6+D6 -> 71.107 | F6: =E6*12 -> 853.284
A7: 5 | B7: =A7*('Per-Shop P&L'!B7) -> 345 | C7: =A7*('Per-Shop P&L'!B8+'Per-Shop P&L'!B9) -> -43.155 | D7: =-(Assumptions!$B$4+Assumptions!$B$5+Assumptions!$B$6+Assumptions!$B$7+Assumptions!$B$8+Assumptions!$B$9+Assumptions!$B$10) -> -110 | E7: =B7+C7+D7 -> 191.845 | F7: =E7*12 -> 2302.14
A8: 10 | B8: =A8*('Per-Shop P&L'!B7) -> 690 | C8: =A8*('Per-Shop P&L'!B8+'Per-Shop P&L'!B9) -> -86.31 | D8: =-(Assumptions!$B$4+Assumptions!$B$5+Assumptions!$B$6+Assumptions!$B$7+Assumptions!$B$8+Assumptions!$B$9+Assumptions!$B$10) -> -110 | E8: =B8+C8+D8 -> 493.69 | F8: =E8*12 -> 5924.28
A9: 25 | B9: =A9*('Per-Shop P&L'!B7) -> 1725 | C9: =A9*('Per-Shop P&L'!B8+'Per-Shop P&L'!B9) -> -215.775 | D9: =-(Assumptions!$B$4+Assumptions!$B$5+Assumptions!$B$6+Assumptions!$B$7+Assumptions!$B$8+Assumptions!$B$9+Assumptions!$B$10) -> -110 | E9: =B9+C9+D9 -> 1399.225 | F9: =E9*12 -> 16790.7
A10: 50 | B10: =A10*('Per-Shop P&L'!B7) -> 3450 | C10: =A10*('Per-Shop P&L'!B8+'Per-Shop P&L'!B9) -> -431.55 | D10: =-(Assumptions!$B$4+Assumptions!$B$5+Assumptions!$B$6+Assumptions!$B$7+Assumptions!$B$8+Assumptions!$B$9+Assumptions!$B$10) -> -110 | E10: =B10+C10+D10 -> 2908.45 | F10: =E10*12 -> 34901.4
A11: 100 | B11: =A11*('Per-Shop P&L'!B7) -> 6900 | C11: =A11*('Per-Shop P&L'!B8+'Per-Shop P&L'!B9) -> -863.1 | D11: =-(Assumptions!$B$4+Assumptions!$B$5+Assumptions!$B$6+Assumptions!$B$7+Assumptions!$B$8+Assumptions!$B$9+Assumptions!$B$10) -> -110 | E11: =B11+C11+D11 -> 5926.9 | F11: =E11*12 -> 71122.8
A12: 200 | B12: =A12*('Per-Shop P&L'!B7) -> 13800 | C12: =A12*('Per-Shop P&L'!B8+'Per-Shop P&L'!B9) -> -1726.2 | D12: =-(Assumptions!$B$4+Assumptions!$B$5+Assumptions!$B$6+Assumptions!$B$7+Assumptions!$B$8+Assumptions!$B$9+Assumptions!$B$10) -> -110 | E12: =B12+C12+D12 -> 11963.8 | F12: =E12*12 -> 143565.6
A14: Breakeven shops (Starter) | B14: =(Assumptions!$B$4+Assumptions!$B$5+Assumptions!$B$6+Assumptions!$B$7+Assumptions!$B$8+Assumptions!$B$9+Assumptions!$B$10)/('Per-Shop P&L'!B10) -> 1.8221273
